odoo8_addon_customize_example-8.0.1.0.0.99.dev17-py2.7-nspkg.pth
odoo8_addon_customize_example-8.0.1.0.0.99.dev17.dist-info/METADATA
odoo8_addon_customize_example-8.0.1.0.0.99.dev17.dist-info/RECORD
odoo8_addon_customize_example-8.0.1.0.0.99.dev17.dist-info/WHEEL
odoo8_addon_customize_example-8.0.1.0.0.99.dev17.dist-info/namespace_packages.txt
odoo8_addon_customize_example-8.0.1.0.0.99.dev17.dist-info/top_level.txt
odoo_addons/customize_example/README.rst
odoo_addons/customize_example/__init__.py
odoo_addons/customize_example/__openerp__.py
odoo_addons/customize_example/backend.py
odoo_addons/customize_example/magento_model.py
odoo_addons/customize_example/partner.py
odoo_addons/customize_example/i18n/am.po
odoo_addons/customize_example/i18n/ar.po
odoo_addons/customize_example/i18n/bg.po
odoo_addons/customize_example/i18n/bs.po
odoo_addons/customize_example/i18n/ca.po
odoo_addons/customize_example/i18n/cs.po
odoo_addons/customize_example/i18n/customize_example.pot
odoo_addons/customize_example/i18n/da.po
odoo_addons/customize_example/i18n/de.po
odoo_addons/customize_example/i18n/el_GR.po
odoo_addons/customize_example/i18n/en_GB.po
odoo_addons/customize_example/i18n/es.po
odoo_addons/customize_example/i18n/es_CR.po
odoo_addons/customize_example/i18n/es_EC.po
odoo_addons/customize_example/i18n/es_MX.po
odoo_addons/customize_example/i18n/es_VE.po
odoo_addons/customize_example/i18n/et.po
odoo_addons/customize_example/i18n/fi.po
odoo_addons/customize_example/i18n/fr.po
odoo_addons/customize_example/i18n/fr_CA.po
odoo_addons/customize_example/i18n/fr_CH.po
odoo_addons/customize_example/i18n/gl.po
odoo_addons/customize_example/i18n/hr.po
odoo_addons/customize_example/i18n/hr_HR.po
odoo_addons/customize_example/i18n/hu.po
odoo_addons/customize_example/i18n/id.po
odoo_addons/customize_example/i18n/it.po
odoo_addons/customize_example/i18n/ja.po
odoo_addons/customize_example/i18n/lt.po
odoo_addons/customize_example/i18n/lv.po
odoo_addons/customize_example/i18n/mk.po
odoo_addons/customize_example/i18n/mn.po
odoo_addons/customize_example/i18n/nb.po
odoo_addons/customize_example/i18n/nb_NO.po
odoo_addons/customize_example/i18n/nl.po
odoo_addons/customize_example/i18n/nl_BE.po
odoo_addons/customize_example/i18n/pl.po
odoo_addons/customize_example/i18n/pt.po
